lunarinfo/__init__.py
lunarinfo/pynocturnal.py
pynocturnal-0.0.1.dist-info/LICENSE
pynocturnal-0.0.1.dist-info/METADATA
pynocturnal-0.0.1.dist-info/WHEEL
pynocturnal-0.0.1.dist-info/top_level.txt
pynocturnal-0.0.1.dist-info/RECORD
