Metadata-Version: 2.1
Name: pynocturnal
Version: 0.0.1
Summary: python package for lunar information
Home-page: https://github.com/PyndyalaCoder/pynocturnal
Author: Siddhu Pendyala
Author-email: elcientifico.pendyala@hotmail.com
License: MIT
Project-URL: Bug Tracker, https://github.com/PyndyalaCoder/pynocturnal/issues
License-File: LICENSE
Requires-Dist: requests
